README.md
setup.cfg
setup.py
md_distributions/Binomialdistribution.py
md_distributions/Gaussiandistribution.py
md_distributions/Generaldistribution.py
md_distributions/__init__.py
md_distributions.egg-info/PKG-INFO
md_distributions.egg-info/SOURCES.txt
md_distributions.egg-info/dependency_links.txt
md_distributions.egg-info/not-zip-safe
md_distributions.egg-info/top_level.txt