Metadata-Version: 1.0
Name: md-distributions
Version: 0.1
Summary: Gaussian binomial distributions
Home-page: UNKNOWN
Author: UNKNOWN
Author-email: UNKNOWN
License: UNKNOWN
Platform: UNKNOWN
